[{"name":"sql.active_record","payload":{"sql":"SELECT  \"users\".* FROM \"users\" WHERE \"users\".\"id\" = $1 LIMIT 1","name":"User Load","connection_id":70224748238260,"statement_name":"a1","binds":[[{"array":false,"name":"id","cast_type":{"precision":null,"scale":null,"limit":null,"range":"-2147483648...2147483648"},"sql_type":"integer","null":false,"default":null,"default_function":"nextval('users_id_seq'::regclass)"},44]],"line":11,"filename":"/Users/Tom/Desktop/Project I/app/controllers/application_controller.rb","method":"authenticate"},"time":"2015-02-12T17:16:28.105+11:00","transaction_id":"c02975f32f40304dbc7f","end":"2015-02-12T17:16:28.105+11:00","children":[],"duration":0.5599999999999999},{"name":"sql.active_record","payload":{"sql":"SELECT \"posts\".* FROM \"posts\"  ORDER BY \"posts\".\"title\" ASC","name":"Post Load","connection_id":70224748238260,"statement_name":null,"binds":[],"line":13,"filename":"/Users/Tom/Desktop/Project I/app/views/posts/index.html.erb","method":"_app_views_posts_index_html_erb___3665936618941670906_70224783404000"},"time":"2015-02-12T17:16:28.114+11:00","transaction_id":"c02975f32f40304dbc7f","end":"2015-02-12T17:16:28.115+11:00","children":[],"duration":0.776},{"name":"sql.active_record","payload":{"sql":"SELECT  \"users\".* FROM \"users\" WHERE \"users\".\"id\" = $1 LIMIT 1","binds":[[{"array":false,"name":"id","cast_type":{"precision":null,"scale":null,"limit":null,"range":"-2147483648...2147483648"},"sql_type":"integer","null":false,"default":null,"default_function":"nextval('users_id_seq'::regclass)"},44]],"name":"CACHE","connection_id":70224748238260,"line":14,"filename":"/Users/Tom/Desktop/Project I/app/views/posts/index.html.erb","method":"block in _app_views_posts_index_html_erb___3665936618941670906_70224783404000"},"time":"2015-02-12T17:16:28.117+11:00","transaction_id":"fafa4481a6ca68485f2e","end":"2015-02-12T17:16:28.117+11:00","children":[],"duration":0.22},{"name":"sql.active_record","payload":{"sql":"SELECT  \"users\".* FROM \"users\" WHERE \"users\".\"id\" = $1 LIMIT 1","name":"User Load","connection_id":70224748238260,"statement_name":"a1","binds":[[{"array":false,"name":"id","cast_type":{"precision":null,"scale":null,"limit":null,"range":"-2147483648...2147483648"},"sql_type":"integer","null":false,"default":null,"default_function":"nextval('users_id_seq'::regclass)"},45]],"line":14,"filename":"/Users/Tom/Desktop/Project I/app/views/posts/index.html.erb","method":"block in _app_views_posts_index_html_erb___3665936618941670906_70224783404000"},"time":"2015-02-12T17:16:28.119+11:00","transaction_id":"c02975f32f40304dbc7f","end":"2015-02-12T17:16:28.119+11:00","children":[],"duration":0.5519999999999999},{"name":"sql.active_record","payload":{"sql":"SELECT  \"users\".* FROM \"users\" WHERE \"users\".\"id\" = $1 LIMIT 1","name":"User Load","connection_id":70224748238260,"statement_name":"a1","binds":[[{"array":false,"name":"id","cast_type":{"precision":null,"scale":null,"limit":null,"range":"-2147483648...2147483648"},"sql_type":"integer","null":false,"default":null,"default_function":"nextval('users_id_seq'::regclass)"},46]],"line":14,"filename":"/Users/Tom/Desktop/Project I/app/views/posts/index.html.erb","method":"block in _app_views_posts_index_html_erb___3665936618941670906_70224783404000"},"time":"2015-02-12T17:16:28.121+11:00","transaction_id":"c02975f32f40304dbc7f","end":"2015-02-12T17:16:28.121+11:00","children":[],"duration":0.449},{"name":"render_template.action_view","payload":{"identifier":"/Users/Tom/Desktop/Project I/app/views/posts/index.html.erb","layout":"layouts/application"},"time":"2015-02-12T17:16:28.114+11:00","transaction_id":"fafa4481a6ca68485f2e","end":"2015-02-12T17:16:28.123+11:00","children":[],"duration":9.467},{"name":"process_action.action_controller","payload":{"controller":"PostsController","action":"index","params":{"controller":"posts","action":"index"},"format":"html","method":"GET","path":"/posts","status":200,"view_runtime":177.64624599745986,"db_runtime":1.2659999999999998},"time":"2015-02-12T17:16:28.104+11:00","transaction_id":"fafa4481a6ca68485f2e","end":"2015-02-12T17:16:28.286+11:00","children":[],"duration":181.479}]