[{"name":"render_template.action_view","payload":{"identifier":"/Users/Tom/Desktop/Project I/code_stock_app/app/views/session/new.html.erb","layout":"layouts/application"},"time":"2015-02-09T10:55:00.323+11:00","transaction_id":"207837d15ac93d372fda","end":"2015-02-09T10:55:00.324+11:00","children":[],"duration":1.7329999999999999},{"name":"process_action.action_controller","payload":{"controller":"SessionController","action":"new","params":{"controller":"session","action":"new"},"format":"html","method":"GET","path":"/login","status":200,"view_runtime":78.69574699998338,"db_runtime":0},"time":"2015-02-09T10:55:00.315+11:00","transaction_id":"207837d15ac93d372fda","end":"2015-02-09T10:55:00.394+11:00","children":[],"duration":79.221}]